ZJountries/ZJountries.py
ZJountries/__init__.py
ZJountries/data.json
ZJountries_py-0.10.8.dist-info/METADATA
ZJountries_py-0.10.8.dist-info/WHEEL
ZJountries_py-0.10.8.dist-info/top_level.txt
ZJountries_py-0.10.8.dist-info/RECORD
