Metadata-Version: 2.1
Name: ZJountries-py
Version: 0.10.8
Summary: ZJountries-api Python package
Author: Zilezia
License: GPL-3.0
Classifier: Programming Language :: Python :: 3
Classifier: License :: OSI Approved :: GNU General Public License v3 (GPLv3)
Classifier: Operating System :: OS Independent
Requires-Python: >=3.6
